odoo/addons/mgmtsystem_nonconformity_product/README.rst
odoo/addons/mgmtsystem_nonconformity_product/__init__.py
odoo/addons/mgmtsystem_nonconformity_product/__manifest__.py
odoo/addons/mgmtsystem_nonconformity_product/i18n/es.po
odoo/addons/mgmtsystem_nonconformity_product/i18n/fa.po
odoo/addons/mgmtsystem_nonconformity_product/i18n/it.po
odoo/addons/mgmtsystem_nonconformity_product/i18n/mgmtsystem_nonconformity_product.pot
odoo/addons/mgmtsystem_nonconformity_product/i18n/pt_BR.po
odoo/addons/mgmtsystem_nonconformity_product/models/__init__.py
odoo/addons/mgmtsystem_nonconformity_product/models/mgmtsystem_nonconformity.py
odoo/addons/mgmtsystem_nonconformity_product/readme/CONTRIBUTORS.md
odoo/addons/mgmtsystem_nonconformity_product/readme/DESCRIPTION.md
odoo/addons/mgmtsystem_nonconformity_product/readme/HISTORY.md
odoo/addons/mgmtsystem_nonconformity_product/readme/USAGE.md
odoo/addons/mgmtsystem_nonconformity_product/static/description/icon.png
odoo/addons/mgmtsystem_nonconformity_product/static/description/index.html
odoo/addons/mgmtsystem_nonconformity_product/views/mgmtsystem_nonconformity_views.xml
odoo_addon_mgmtsystem_nonconformity_product-18.0.1.0.0.2.dist-info/METADATA
odoo_addon_mgmtsystem_nonconformity_product-18.0.1.0.0.2.dist-info/WHEEL
odoo_addon_mgmtsystem_nonconformity_product-18.0.1.0.0.2.dist-info/top_level.txt
odoo_addon_mgmtsystem_nonconformity_product-18.0.1.0.0.2.dist-info/RECORD
